setup.py
shah_distributions/Binomialdistribution.py
shah_distributions/Gaussiandistribution.py
shah_distributions/Generaldistribution.py
shah_distributions/__init__.py
shah_distributions.egg-info/PKG-INFO
shah_distributions.egg-info/SOURCES.txt
shah_distributions.egg-info/dependency_links.txt
shah_distributions.egg-info/not-zip-safe
shah_distributions.egg-info/top_level.txt