Metadata-Version: 1.0
Name: shah-distributions
Version: 0.1
Summary: Gaussian and Binomial distributions
Home-page: UNKNOWN
Author: Shahzeb Akhtar
Author-email: shahzeb.akhtar@gmail.com
License: UNKNOWN
Platform: UNKNOWN
